Win32Security/__init__.py
Win32Security/__main__.py
win32security-2.0.1.dist-info/METADATA
win32security-2.0.1.dist-info/WHEEL
win32security-2.0.1.dist-info/licenses/LICENSE
win32security-2.0.1.dist-info/RECORD
