Metadata-Version: 2.1
Name: Win32Security
Version: 2.0.1
Summary: Data secured by the Windows API
Project-URL: Homepage, https://github.com/LassaInora/Win32Security
Project-URL: Bug Tracker, https://github.com/LassaInora/Win32Security/issues
Author-email: Axelle Viandier <lassainora@lassainora.fr>
License-File: LICENSE
Classifier: License :: OSI Approved :: GNU General Public License v3 (GPLv3)
Classifier: Operating System :: OS Independent
Classifier: Programming Language :: Python :: 3
Requires-Python: >=3.6
